{
  "schemaVersion": 1,
  "id": "verstak.sync",
  "name": "Sync",
  "version": "0.1.0",
  "apiVersion": "0.1.0",
  "source": "official",
  "provides": ["verstak/sync/v1", "verstak/sync.status/v1"],
  "requires": ["verstak/core/files/v1"],
  "permissions": ["files.read", "files.write", "network.remote", "storage.namespace", "sync.participate", "ui.register"],
  "frontend": { "entry": "frontend/dist/index.js" },
  "contributes": {
    "settingsPanels": [{ "id": "verstak.sync.settings", "title": "Sync", "component": "SyncSettings" }],
    "statusBarItems": [{ "id": "verstak.sync.status", "label": "Sync", "position": "right" }]
  }
}
